zqueue.py
zqueue-1.2.0.dist-info/LICENSE
zqueue-1.2.0.dist-info/METADATA
zqueue-1.2.0.dist-info/WHEEL
zqueue-1.2.0.dist-info/top_level.txt
zqueue-1.2.0.dist-info/RECORD
