Metadata-Version: 2.1
Name: zqueue
Version: 1.2.0
Summary: 本地队列模块
Requires-Dist: zblocker
